hats/__init__.py
hats/config_loader.py
hats/core.py
hats/dynamic_interface.py
hats/plugin_loader.py
hats/security.py
hats/tool_manager.py
hats/categories/__init__.py
hats/categories/exploitation.py
hats/categories/post_exploit.py
hats/categories/reporting.py
hats/categories/scanning.py
hats/utils/__init__.py
hats/utils/detector.py
hats/utils/logger.py
hats_framework-2.1.0.dist-info/licenses/LICENSE
hats_framework-2.1.0.dist-info/METADATA
hats_framework-2.1.0.dist-info/WHEEL
hats_framework-2.1.0.dist-info/entry_points.txt
hats_framework-2.1.0.dist-info/top_level.txt
hats_framework-2.1.0.dist-info/RECORD
