Metadata-Version: 2.4
Name: hats-framework
Version: 2.1.0
Summary: Professional cybersecurity automation framework with 36 CLI tools and enterprise security
Home-page: https://github.com/hats-security/hats-framework
Author: HATS Security Team
Author-email: HATS Security Team <security@hats-framework.org>
Maintainer-email: HATS Security Team <security@hats-framework.org>
License-Expression: MIT
Project-URL: Homepage, https://github.com/hats-security/hats-framework
Project-URL: Documentation, https://hats-framework.readthedocs.io/
Project-URL: Repository, https://github.com/hats-security/hats-framework.git
Project-URL: Bug Tracker, https://github.com/hats-security/hats-framework/issues
Project-URL: Security, https://github.com/hats-security/hats-framework/security
Keywords: cybersecurity,penetration-testing,security-tools,automation,hacking-tools,vulnerability-scanner,network-security,web-security,security-framework,nmap,gobuster,sqlmap,nikto,john-the-ripper,hydra,metasploit,kali-linux,security-audit,opsec,red-team,blue-team,cli-tools
Classifier: Development Status :: 5 - Production/Stable
Classifier: Intended Audience :: Information Technology
Classifier: Intended Audience :: System Administrators
Classifier: Intended Audience :: Developers
Classifier: Operating System :: POSIX :: Linux
Classifier: Operating System :: MacOS
Classifier: Programming Language :: Python :: 3
Classifier: Programming Language :: Python :: 3.7
Classifier: Programming Language :: Python :: 3.8
Classifier: Programming Language :: Python :: 3.9
Classifier: Programming Language :: Python :: 3.10
Classifier: Programming Language :: Python :: 3.11
Classifier: Programming Language :: Python :: 3.12
Classifier: Topic :: Security
Classifier: Topic :: System :: Systems Administration
Classifier: Topic :: System :: Networking :: Monitoring
Classifier: Topic :: Software Development :: Libraries :: Python Modules
Classifier: Environment :: Console
Requires-Python: >=3.7
License-File: LICENSE
Requires-Dist: pyyaml>=6.0
Requires-Dist: requests>=2.28.0
Requires-Dist: psutil>=5.9.0
Requires-Dist: colorama>=0.4.5
Requires-Dist: rich>=12.0.0
Requires-Dist: click>=8.1.0
Provides-Extra: dev
Requires-Dist: pytest>=7.0.0; extra == "dev"
Requires-Dist: pytest-cov>=4.0.0; extra == "dev"
Requires-Dist: pytest-mock>=3.8.0; extra == "dev"
Requires-Dist: black>=22.0.0; extra == "dev"
Requires-Dist: flake8>=5.0.0; extra == "dev"
Requires-Dist: mypy>=0.971; extra == "dev"
Requires-Dist: pre-commit>=2.20.0; extra == "dev"
Provides-Extra: reporting
Requires-Dist: jinja2>=3.1.0; extra == "reporting"
Requires-Dist: matplotlib>=3.5.0; extra == "reporting"
Requires-Dist: plotly>=5.0.0; extra == "reporting"
Provides-Extra: database
Requires-Dist: sqlalchemy>=1.4.0; extra == "database"
Provides-Extra: web
Requires-Dist: flask>=2.2.0; extra == "web"
Requires-Dist: flask-restful>=0.3.9; extra == "web"
Provides-Extra: advanced
Requires-Dist: scapy>=2.4.0; extra == "advanced"
Requires-Dist: python-nmap>=0.7.0; extra == "advanced"
Requires-Dist: cryptography>=37.0.0; extra == "advanced"
Requires-Dist: pycryptodome>=3.15.0; extra == "advanced"
Requires-Dist: lxml>=4.9.0; extra == "advanced"
Requires-Dist: pandas>=1.4.0; extra == "advanced"
Dynamic: author
Dynamic: home-page
Dynamic: license-file
Dynamic: requires-python
